{
    "parameterSets": {
        "screenshot": {
            "Base_Height": "0.84",
            "Column_Label": "",
            "Column_Label_Height_Multiplier": "0.3",
            "Ending_Value": "4",
            "Font": "Arial:style=Bold",
            "Iota": "0.001",
            "Label_Sections": "false",
            "Orient_for_Screenshot": "true",
            "Preview_Quality_Value": "24",
            "Render_Quality_Value": "24",
            "Screenshot_Vpd": "140",
            "Screenshot_Vpf": "22.5",
            "Screenshot_Vpr": "[75, 0, 300]",
            "Screenshot_Vpt": "[0, 0, 15]",
            "Section_Height": "8",
            "Section_Label_Height_Multiplier": "0.3",
            "Section_Label_Prefix": "",
            "Section_Label_Suffix": "",
            "Starting_Value": "1",
            "Tower_Label": "",
            "Tower_Label_Height_Multiplier": "0.6",
            "Tower_Width_Multiplier": "5",
            "Value_Change": "1",
            "Wall_Thickness": "0.6"
        },
        "Linear Advance Tower - K 0.0-0.2": {
            "Column_Label": "0.0 - 0.2",
            "Column_Label_Height_Multiplier": "0.301",
            "Ending_Value": "0.2",
            "Font": "Arial:style=Bold",
            "Iota": "0.001",
            "Label_Sections": "true",
            "Orient_for_Screenshot": "false",
            "Preview_Quality_Value": "24",
            "Render_Quality_Value": "24",
            "Screenshot_Vpd": "140",
            "Screenshot_Vpf": "22.5",
            "Screenshot_Vpr": "[75, 0, 300]",
            "Screenshot_Vpt": "[0, 0, 15]",
            "Section_Height": "8.4",
            "Section_Label_Height_Multiplier": "0.401",
            "Section_Label_Prefix": "",
            "Section_Label_Suffix": "",
            "Starting_Value": "0",
            "Tower_Label": "LINEAR ADV",
            "Tower_Label_Height_Multiplier": "0.601",
            "Tower_Size": "70",
            "Value_Change": "0.02"
        },
        "Linear Advance Tower - K 0.0-2.0": {
            "Column_Label": "0.0 - 2.0",
            "Column_Label_Height_Multiplier": "0.301",
            "Ending_Value": "2",
            "Font": "Arial:style=Bold",
            "Iota": "0.001",
            "Label_Sections": "true",
            "Orient_for_Screenshot": "false",
            "Preview_Quality_Value": "24",
            "Render_Quality_Value": "24",
            "Screenshot_Vpd": "140",
            "Screenshot_Vpf": "22.5",
            "Screenshot_Vpr": "[75, 0, 300]",
            "Screenshot_Vpt": "[0, 0, 15]",
            "Section_Height": "8.4",
            "Section_Label_Height_Multiplier": "0.401",
            "Section_Label_Prefix": "",
            "Section_Label_Suffix": "",
            "Starting_Value": "0",
            "Tower_Label": "LINEAR ADV",
            "Tower_Label_Height_Multiplier": "0.601",
            "Tower_Size": "70",
            "Value_Change": "0.2"
        }
    },
    "fileFormatVersion": "1"
}
